{
"name": "tiles.mbtiles",
"description": "tiles.mbtiles",
"version": "2",
"minzoom": "6",
"maxzoom": "16",
"center": "19.877014,41.345887,16",
"bounds": "19.259033,39.643768,21.060791,42.662241",
"type": "overlay",
"format": "pbf",
"generator": "tile-join v1.36.0",
"generator_options": "tippecanoe --no-progress-indicator --no-feature-limit --no-tile-size-limit --force '--simplification=2' '--minimum-zoom=6' '--maximum-zoom=16' '--base-zoom=16' --hilbert '--output=tiles.mbtiles'; tile-join --force --no-tile-compression '--output-to-directory=docs/zxy' --no-tile-size-limit tiles.mbtiles",
"json": "{\"vector_layers\": [ { \"id\": \"AdministrativeBoundary\", \"description\": \"\", \"minzoom\": 6, \"maxzoom\": 16, \"fields\": {\"AdministrativeHierachyLevel\": \"String\"} }, { \"id\": \"AerodromeArea\", \"description\": \"\", \"minzoom\": 13, \"maxzoom\": 16, \"fields\": {\"AsigAirportTypeValue\": \"String\"} }, { \"id\": \"AerodromeNode\", \"description\": \"\", \"minzoom\": 16, \"maxzoom\": 16, \"fields\": {} }, { \"id\": \"AerodromePoint\", \"description\": \"\", \"minzoom\": 16, \"maxzoom\": 16, \"fields\": {\"AsigAirportTypeValue\": \"String\"} }, { \"id\": \"AgriBuilding\", \"description\": \"\", \"minzoom\": 14, \"maxzoom\": 16, \"fields\": {\"GeographicalName\": \"String\", \"TypeOfAgriBuildingValue\": \"String\", \"sarea\": \"Number\"} }, { \"id\": \"Appurtenance\", \"description\": \"\", \"minzoom\": 16, \"maxzoom\": 16, \"fields\": {\"AppurtenanceTypeValue\": \"String\"} }, { \"id\": \"ApronArea\", \"description\": \"\", \"minzoom\": 13, \"maxzoom\": 16, \"fields\": {} }, { \"id\": \"AquacultureInstallation\", \"description\": \"\", \"minzoom\": 16, \"maxzoom\": 16, \"fields\": {\"AquacultureInstallationValue\": \"String\"} }, { \"id\": \"AsigAreaBuildingFeature\", \"description\": \"\", \"minzoom\": 14, \"maxzoom\": 16, \"fields\": {\"AsigAreaBuildingFeatureTypeValue\": \"String\", \"GeographicalName\": \"String\", \"sarea\": \"Number\"} }, { \"id\": \"AsigAreaTransportFeature\", \"description\": \"\", \"minzoom\": 15, \"maxzoom\": 16, \"fields\": {\"AsigAreaTransportFeatureTypeValue\": \"String\"} }, { \"id\": \"AsigLinearFenceFeature\", \"description\": \"\", \"minzoom\": 16, \"maxzoom\": 16, \"fields\": {\"AsigLinearFenceFeatureTypeValue\": \"String\"} }, { \"id\": \"AsigLinearTopographicFeature\", \"description\": \"\", \"minzoom\": 14, \"maxzoom\": 16, \"fields\": {\"AsigLinearTopographicFeatureTypeValue\": \"String\"} }, { \"id\": \"AsigLinearTransportFeature\", \"description\": \"\", \"minzoom\": 14, \"maxzoom\": 16, \"fields\": {\"AsigLinearTransportFeatureTypeValue\": \"String\"} }, { \"id\": \"AsigPointCartographicFeature\", \"description\": \"\", \"minzoom\": 16, \"maxzoom\": 16, \"fields\": {\"AsigPointCartographicFeatureTypeValue\": \"String\", \"GeographicalName\": \"String\"} }, { \"id\": \"AsigPointReligiousFeature\", \"description\": \"\", \"minzoom\": 16, \"maxzoom\": 16, \"fields\": {\"AsigPointReligiousFeatureTypeValue\": \"String\", \"GeographicalName\": \"String\"} }, { \"id\": \"Beacon\", \"description\": \"\", \"minzoom\": 16, \"maxzoom\": 16, \"fields\": {} }, { \"id\": \"BreakLine\", \"description\": \"\", \"minzoom\": 16, \"maxzoom\": 16, \"fields\": {\"BreakLineTypevalue\": \"String\"} }, { \"id\": \"Building\", \"description\": \"\", \"minzoom\": 14, \"maxzoom\": 16, \"fields\": {\"Building\": \"String\", \"GeographicalName\": \"String\", \"sarea\": \"Number\"} }, { \"id\": \"BuildingPart\", \"description\": \"\", \"minzoom\": 14, \"maxzoom\": 16, \"fields\": {\"BuildingPart\": \"String\", \"GeographicalName\": \"String\", \"sarea\": \"Number\"} }, { \"id\": \"Cabinet\", \"description\": \"\", \"minzoom\": 16, \"maxzoom\": 16, \"fields\": {} }, { \"id\": \"CablewayLink\", \"description\": \"\", \"minzoom\": 16, \"maxzoom\": 16, \"fields\": {\"AsigCablewayPurposeValue\": \"String\", \"CablewayTypevalue\": \"String\"} }, { \"id\": \"CablewayNode\", \"description\": \"\", \"minzoom\": 16, \"maxzoom\": 16, \"fields\": {\"AsigCablewayNodePurposeValue\": \"String\"} }, { \"id\": \"ContourLine\", \"description\": \"\", \"minzoom\": 13, \"maxzoom\": 16, \"fields\": {\"ContourLineTypeValue\": \"String\", \"HeightValue\": \"Number\"} }, { \"id\": \"CrossingA\", \"description\": \"\", \"minzoom\": 13, \"maxzoom\": 16, \"fields\": {\"CrossingTypevalue\": \"String\"} }, { \"id\": \"CrossingL\", \"description\": \"\", \"minzoom\": 13, \"maxzoom\": 16, \"fields\": {\"CrossingTypevalue\": \"String\"} }, { \"id\": \"DamOrWeir\", \"description\": \"\", \"minzoom\": 13, \"maxzoom\": 16, \"fields\": {} }, { \"id\": \"DrainageBasin\", \"description\": \"\", \"minzoom\": 13, \"maxzoom\": 16, \"fields\": {} }, { \"id\": \"Duct\", \"description\": \"\", \"minzoom\": 16, \"maxzoom\": 16, \"fields\": {\"UtilityDeliveryTypeValue\": \"String\"} }, { \"id\": \"ElevationGridCoverage\", \"description\": \"\", \"minzoom\": 16, \"maxzoom\": 16, \"fields\": {\"ElevationPropertyTypeValue\": \"String\", \"SurfaceTypeValue\": \"String\"} }, { \"id\": \"Embankment\", \"description\": \"\", \"minzoom\": 13, \"maxzoom\": 16, \"fields\": {} }, { \"id\": \"EnvironmentalManagementFacilityA\", \"description\": \"\", \"minzoom\": 16, \"maxzoom\": 16, \"fields\": {\"EnvironmentalManagementFacilityTypeValue\": \"String\"} }, { \"id\": \"EnvironmentalManagementFacilityP\", \"description\": \"\", \"minzoom\": 16, \"maxzoom\": 16, \"fields\": {\"EnvironmentalManagementFacilityTypeValue\": \"String\"} }, { \"id\": \"FallsA\", \"description\": \"\", \"minzoom\": 13, \"maxzoom\": 16, \"fields\": {\"AsigFallTypevalue\": \"String\", \"fall\": \"String\"} }, { \"id\": \"Ford\", \"description\": \"\", \"minzoom\": 13, \"maxzoom\": 16, \"fields\": {} }, { \"id\": \"GovernmentalService\", \"description\": \"\", \"minzoom\": 16, \"maxzoom\": 16, \"fields\": {\"GeographicalName\": \"String\", \"ServiceTypeList\": \"String\"} }, { \"id\": \"HydroNode\", \"description\": \"\", \"minzoom\": 16, \"maxzoom\": 16, \"fields\": {\"HydroNodeCategoryValue\": \"String\"} }, { \"id\": \"InstallationPart\", \"description\": \"\", \"minzoom\": 16, \"maxzoom\": 16, \"fields\": {\"InstallationPartValue\": \"String\"} }, { \"id\": \"LandCoverUnit\", \"description\": \"\", \"minzoom\": 9, \"maxzoom\": 16, \"fields\": {\"LandCoverClass\": \"String\"} }, { \"id\": \"LandwaterBoundary\", \"description\": \"\", \"minzoom\": 13, \"maxzoom\": 16, \"fields\": {\"OriginValue\": \"String\", \"WaterLevelvalue\": \"String\"} }, { \"id\": \"Manhole\", \"description\": \"\", \"minzoom\": 16, \"maxzoom\": 16, \"fields\": {} }, { \"id\": \"NamedPlace\", \"description\": \"\", \"minzoom\": 12, \"maxzoom\": 16, \"fields\": {\"GeographicalName\": \"String\", \"NamedPlaceTypeValue\": \"String\"} }, { \"id\": \"OilGasChemicalsPipe\", \"description\": \"\", \"minzoom\": 16, \"maxzoom\": 16, \"fields\": {\"AsigOilGasChemicalsPipeTypeValue\": \"String\", \"OilGasChemicalsProductTypeValue\": \"String\", \"UtilityDeliveryTypeValue\": \"String\"} }, { \"id\": \"Order1_State_code\", \"description\": \"\", \"minzoom\": 16, \"maxzoom\": 16, \"fields\": {\"Entity\": \"String\", \"FID_\": \"Number\", \"Layer\": \"String\", \"attrvalue\": \"String\", \"code\": \"String\"} }, { \"id\": \"Order3_Municipal_code\", \"description\": \"\", \"minzoom\": 16, \"maxzoom\": 16, \"fields\": {\"Autoriteti\": \"String\", \"Emertim\": \"String\", \"Emertimi\": \"String\", \"Fillimi_I_\": \"String\", \"ID_Alterna\": \"Number\", \"Inspire_ID\": \"String\", \"Kodi_Komb\": \"String\", \"Niveli_Nac\": \"String\", \"Shape_Leng\": \"Number\", \"Shteti\": \"String\", \"attrvalue\": \"String\", \"code\": \"String\", \"name\": \"String\"} }, { \"id\": \"Pipe\", \"description\": \"\", \"minzoom\": 16, \"maxzoom\": 16, \"fields\": {\"UtilityDeliveryTypeValue\": \"String\"} }, { \"id\": \"Pole\", \"description\": \"\", \"minzoom\": 16, \"maxzoom\": 16, \"fields\": {\"AsigPoleTypeValue\": \"String\"} }, { \"id\": \"PortArea\", \"description\": \"\", \"minzoom\": 16, \"maxzoom\": 16, \"fields\": {} }, { \"id\": \"ProductionBuilding\", \"description\": \"\", \"minzoom\": 14, \"maxzoom\": 16, \"fields\": {\"GeographicalName\": \"String\", \"sarea\": \"Number\"} }, { \"id\": \"ProductionInstallation\", \"description\": \"\", \"minzoom\": 15, \"maxzoom\": 16, \"fields\": {\"AsigProductionInstallationTypeValue\": \"String\"} }, { \"id\": \"RailwayArea\", \"description\": \"\", \"minzoom\": 15, \"maxzoom\": 16, \"fields\": {} }, { \"id\": \"RailwayLink\", \"description\": \"\", \"minzoom\": 13, \"maxzoom\": 16, \"fields\": {} }, { \"id\": \"RailwayNode\", \"description\": \"\", \"minzoom\": 16, \"maxzoom\": 16, \"fields\": {} }, { \"id\": \"RailwayStationArea\", \"description\": \"\", \"minzoom\": 13, \"maxzoom\": 16, \"fields\": {} }, { \"id\": \"RailwayStationNode\", \"description\": \"\", \"minzoom\": 16, \"maxzoom\": 16, \"fields\": {} }, { \"id\": \"RailwayYardArea\", \"description\": \"\", \"minzoom\": 13, \"maxzoom\": 16, \"fields\": {} }, { \"id\": \"RailwayYardNode\", \"description\": \"\", \"minzoom\": 16, \"maxzoom\": 16, \"fields\": {} }, { \"id\": \"RapidsA\", \"description\": \"\", \"minzoom\": 14, \"maxzoom\": 16, \"fields\": {} }, { \"id\": \"RiverBasin\", \"description\": \"\", \"minzoom\": 16, \"maxzoom\": 16, \"fields\": {} }, { \"id\": \"RoadArea\", \"description\": \"\", \"minzoom\": 15, \"maxzoom\": 16, \"fields\": {} }, { \"id\": \"RoadLink\", \"description\": \"\", \"minzoom\": 13, \"maxzoom\": 16, \"fields\": {\"GeographicalName\": \"String\"} }, { \"id\": \"RoadNode\", \"description\": \"\", \"minzoom\": 16, \"maxzoom\": 16, \"fields\": {} }, { \"id\": \"RoadServiceArea\", \"description\": \"\", \"minzoom\": 13, \"maxzoom\": 16, \"fields\": {} }, { \"id\": \"RunwayArea\", \"description\": \"\", \"minzoom\": 13, \"maxzoom\": 16, \"fields\": {} }, { \"id\": \"Shore\", \"description\": \"\", \"minzoom\": 14, \"maxzoom\": 16, \"fields\": {\"ShoreTypeValue\": \"String\"} }, { \"id\": \"ShorelineConstruction\", \"description\": \"\", \"minzoom\": 14, \"maxzoom\": 16, \"fields\": {} }, { \"id\": \"Sluice\", \"description\": \"\", \"minzoom\": 14, \"maxzoom\": 16, \"fields\": {} }, { \"id\": \"SpotElevation\", \"description\": \"\", \"minzoom\": 16, \"maxzoom\": 16, \"fields\": {\"HeightValue\": \"Number\", \"SpotElevationClassValue\": \"String\", \"SpotElevationType\": \"String\"} }, { \"id\": \"StandingWaterA\", \"description\": \"\", \"minzoom\": 14, \"maxzoom\": 16, \"fields\": {\"GeographicalName\": \"String\", \"HydrologicalPersistenceValue\": \"String\"} }, { \"id\": \"TaxiwayArea\", \"description\": \"\", \"minzoom\": 13, \"maxzoom\": 16, \"fields\": {} }, { \"id\": \"Tower\", \"description\": \"\", \"minzoom\": 16, \"maxzoom\": 16, \"fields\": {} }, { \"id\": \"VehicleTrafficArea\", \"description\": \"\", \"minzoom\": 6, \"maxzoom\": 16, \"fields\": {\"AsigVehicleTrafficTypevalue\": \"String\"} }, { \"id\": \"WaterManagementInstallationP\", \"description\": \"\", \"minzoom\": 14, \"maxzoom\": 16, \"fields\": {\"WaterSourceValue\": \"String\"} }, { \"id\": \"WatercourseA\", \"description\": \"\", \"minzoom\": 14, \"maxzoom\": 16, \"fields\": {\"ConditionOfFacilityValue\": \"String\", \"HydrologicalPersistenceValue\": \"String\", \"VerticalPositionValue\": \"String\"} }, { \"id\": \"WatercourseL\", \"description\": \"\", \"minzoom\": 14, \"maxzoom\": 16, \"fields\": {\"ConditionOfFacilityValue\": \"String\", \"HydrologicalPersistenceValue\": \"String\", \"VerticalPositionValue\": \"String\", \"WidthRange\": \"String\", \"WidthValue\": \"Number\"} }, { \"id\": \"WatercourseLink\", \"description\": \"\", \"minzoom\": 14, \"maxzoom\": 16, \"fields\": {\"GeographicalName\": \"String\"} }, { \"id\": \"WatercourseSeparatedCrossing\", \"description\": \"\", \"minzoom\": 14, \"maxzoom\": 16, \"fields\": {} } ],\"tilestats\": {\"layerCount\": 76,\"layers\": [{\"layer\": \"AdministrativeBoundary\",\"count\": 25385,\"geometry\": \"LineString\",\"attributeCount\": 1,\"attributes\": [{\"attribute\": \"AdministrativeHierachyLevel\",\"count\": 3,\"type\": \"string\",\"values\": [\"1stOrder(National Boundary)\",\"2ndOrder(Administrative Boundary)\",\"3rdOrder(Municipality Boundary)\"]}]},{\"layer\": \"AerodromeArea\",\"count\": 111,\"geometry\": \"Polygon\",\"attributeCount\": 1,\"attributes\": [{\"attribute\": \"AsigAirportTypeValue\",\"count\": 2,\"type\": \"string\",\"values\": [\"airport\",\"heliport\"]}]},{\"layer\": \"AerodromeNode\",\"count\": 5,\"geometry\": \"Point\",\"attributeCount\": 0,\"attributes\": []},{\"layer\": \"AerodromePoint\",\"count\": 16,\"geometry\": \"Point\",\"attributeCount\": 1,\"attributes\": [{\"attribute\": \"AsigAirportTypeValue\",\"count\": 2,\"type\": \"string\",\"values\": [\"airport\",\"heliport\"]}]},{\"layer\": \"AgriBuilding\",\"count\": 4075,\"geometry\": \"Polygon\",\"attributeCount\": 3,\"attributes\": [{\"attribute\": \"GeographicalName\",\"count\": 6,\"type\": \"string\",\"values\": [\"Depo Uji \\\"Koder Kashar\\\"\",\"Depo Uji Kashar\",\"Depo Uji Paskuqan\",\"Depo Uji Tiranë\",\"Depo Uji, Komuna Kashar\",\"Ujësjellësi  i Tiranës\"]},{\"attribute\": \"TypeOfAgriBuildingValue\",\"count\": 8,\"type\": \"string\",\"values\": [\"1_animalHousing\",\"2_2_supplyStorage\",\"2_3_fuelTank\",\"2_4_waterTank\",\"2_storage\",\"7_greenhouse\",\"8_shed\",\"9_other\"]},{\"attribute\": \"sarea\",\"count\": 1000,\"type\": \"number\",\"values\": [1.25454161948076,1.5894397612616214,1.603653801056993,1.7651115998039409,10.139753078629992,10.18870719651493,10.19951680167332,10.579752101466778,10.612517999922082,10.726279000407555,10.80950239970388,10.810350878738096,10.845391101909647,10.906626399043525,10.915204689347274,10.944752598430457,10.960562994742383,10.998049700165677,100.26109800825999,100.40594739380949,100.80808976148467,100.97398897955594,1001.7016675106312,1003.3675932226597,1006.1888094835049,1009.2291707859854,101.09944718198754,101.49913661510516,101.51268816205823,101.52573074447523,101.77153066955714,101.84430666404123,1014.6880014075962,1016.9624159345148,102.0613318501088,102.22222214047557,102.62556988864644,102.75995113238449,102.8090429470307,1022.1999559220684,1022.9317829114029,103.04670379189146,103.10146987082982,103.17085677946059,103.30638999893334,103.95784803057168,1030.2647460676809,1031.1782581743883,1034.3725041474209,1037.7325008416086,104.23044600305474,104.23786073367789,104.36002620304441,104.4402869927739,104.52637258713404,104.62400214226217,104.69172270475977,104.95503900154361,1040.4371461660608,1042.054988778419,1046.7480906402009,1047.0865921307369,105.16382596579114,105.35208960912039,105.55668993530432,1056.2357106180078,106.03791770735708,106.1901481848054,106.44598207038253,106.6449902744002,106.75049728111938,106.79118069227022,106.8014871982643,106.85781484130462,106.95601959190047,1060.0623776003234,1062.8868711637647,1067.2662314129726,107.0236319379652,107.03368255966652,107.05221225957064,107.16184859770626,107.29461435662454,107.34996239604986,107.36577101218885,107.42986556779042,107.48439668363986,107.50260653565869,107.78584606534969,107.8801138224909,1079.3353414946867,108.30420839749601,108.65841455949064,108.85450887976335,108.88628120619738,1085.3139419080576,1085.3591149988486,1089.733198179009,109.0600895926084,109.67970361664098],\"min\": 1.25454161948076,\"max\": 30455.324847182434}]},{\"layer\": \"Appurtenance\",\"count\": 1281,\"geometry\": \"Point\",\"attributeCount\": 1,\"attributes\": [{\"attribute\": \"AppurtenanceTypeValue\",\"count\": 8,\"type\": \"string\",\"values\": [\"antenna(Telecommunication)\",\"fountain(Water)\",\"gasStation(OilGasChemical)\",\"hydrant(Water)\",\"pumpStation(Water)\",\"subStation(Electricity)\",\"transformer(Electricity)\",\"treatmentPlant(Water)\"]}]},{\"layer\": \"ApronArea\",\"count\": 70,\"geometry\": \"Polygon\",\"attributeCount\": 0,\"attributes\": []},{\"layer\": \"AquacultureInstallation\",\"count\": 31,\"geometry\": \"Point\",\"attributeCount\": 1,\"attributes\": [{\"attribute\": \"AquacultureInstallationValue\",\"count\": 3,\"type\": \"string\",\"values\": [\"ponds\",\"recirculationSystem\",\"tanksAndRaceways\"]}]},{\"layer\": \"AsigAreaBuildingFeature\",\"count\": 22313,\"geometry\": \"Polygon\",\"attributeCount\": 3,\"attributes\": [{\"attribute\": \"AsigAreaBuildingFeatureTypeValue\",\"count\": 4,\"type\": \"string\",\"values\": [\"pool\",\"ruin\",\"underconstructionBuilding\",\"wallLessBuilding\"]},{\"attribute\": \"GeographicalName\",\"count\": 21,\"type\": \"string\",\"values\": [\" \",\"\\\"Alfa\\\"\",\"\\\"Koldashi\\\"\",\"Banka Shqipërisë,Thesari i Shtetit\",\"Cirku Kombëtar\",\"Firma \\\"Ank\\\"\",\"Hilton Garden Inn Tirana\",\"Kolegji \\\"Don Bosco\\\", Parkim\",\"Pazari i Ri\",\"QKKF\",\"Reparti Ushtarak Nr.6630\",\"Shega Air\",\"Shk. 9 Vjecare \\\"Kongresi i Manastirit\\\"\",\"Shk. 9-Vjeçare \\\"Rilindja\\\" Sallmone\",\"Shk. Flabina/ Skënderbej\",\"Shk. e Mesme \\\"Ismail Qemali\\\"\",\"Stadiumi \\\"Qemal Stafa\\\"\",\"Tregu Fruta-Perime \\\"Mine Peza\\\"\",\"Tregu Laprake\",\"Tregu i Gjësë Sëe Gjallë\",\"Tregu i Përzier Nj.Nr.6\"]},{\"attribute\": \"sarea\",\"count\": 1000,\"type\": \"number\",\"values\": [0.051150345089911227,0.1289477402776687,0.3805285547884793,0.6305000003311783,0.7157974151961657,0.7642854002642728,0.8259452802280052,0.8397574199323226,0.8502208603182354,0.8609326600714848,0.9199330797890779,0.9287335804676171,0.9743717398135422,0.9814590401345036,0.9854747205346923,0.9944996400675332,1.001298570729148,1.0092901395740777,1.0370310609652163,1.0391379607045659,1.0429999192036186,1.0508918797063743,1.0518601998997808,1.0551384599390897,1.0741326606914664,1.0989925599786179,1.0996509491230056,1.1070784602826359,1.1073944403469019,1.1147605594732229,1.1162833198418137,1.118353040214679,1.1309664410066916,1.137816500134211,1.140025380441646,1.1405195799019057,1.1411343194104733,1.1478267015111626,1.1507391791954969,1.16146573937404,1.1674866600342396,1.1720822804112186,1.1723919591202075,1.175443460781061,1.186049239422368,1.1862281991428352,1.1905988005405189,1.1965047995411276,1.2002342396728195,1.2090593999920918,1.2114518790199152,1.2312934415828115,1.2336209591355818,1.2350896792033908,1.2387656012595126,1.2404307180978048,1.2475423194044347,1.2576785792123249,1.260966379808656,1.2621758594390298,1.263069300578066,1.2641549204589109,1.2723188993198112,1.2743762989800694,1.2784841199826125,1.2836741999973165,1.2863326807105838,1.2874053985288839,1.290886879066686,1.2920899978703263,1.3051164410456209,1.308157119961654,1.3183943201453988,1.3209259206245859,1.3272789986650498,1.3287949597114633,1.3442942402429008,1.3451435185803283,1.347725320034955,1.3495937997090713,1.3522929798058277,1.3537095801627508,1.356691060672986,1.3640887595784868,1.3653648397243879,1.3767217194015,1.37803943938302,1.387676600131934,1.3885124388228259,1.38931490040228,1.3893838159176256,1.395188159164317,1.3970623405223637,1.402093297948149,1.4044531114349397,1.4107320001166613,1.4128611200663422,1.4139500998824999,1.4152863793036368,1.4241754204986932],\"min\": 0.051150345089911227,\"max\": 8735.72109860144}]},{\"layer\": \"AsigAreaTransportFeature\",\"count\": 2791,\"geometry\": \"Polygon\",\"attributeCount\": 1,\"attributes\": [{\"attribute\": \"AsigAreaTransportFeatureTypeValue\",\"count\": 4,\"type\": \"string\",\"values\": [\"pedestrianPassageOverRoad\",\"pedestrianPassageUnderRoad\",\"squares\",\"stairs\"]}]},{\"layer\": \"AsigLinearFenceFeature\",\"count\": 317424,\"geometry\": \"LineString\",\"attributeCount\": 1,\"attributes\": [{\"attribute\": \"AsigLinearFenceFeatureTypeValue\",\"count\": 8,\"type\": \"string\",\"values\": [\" \",\"CemeteryEnclosure\",\"HistoricWall\",\"fence\",\"hedge\",\"lineOfConiferousTrees\",\"lineOfDeciduousTrees\",\"wall\"]}]},{\"layer\": \"AsigLinearTopographicFeature\",\"count\": 118629,\"geometry\": \"LineString\",\"attributeCount\": 1,\"attributes\": [{\"attribute\": \"AsigLinearTopographicFeatureTypeValue\",\"count\": 5,\"type\": \"string\",\"values\": [\"Landslide\",\"Ridge\",\"RockyScarp/escarpment\",\"SlopeOver2m\",\"SlopeUpTo2m\"]}]},{\"layer\": \"AsigLinearTransportFeature\",\"count\": 104831,\"geometry\": \"LineString\",\"attributeCount\": 1,\"attributes\": [{\"attribute\": \"AsigLinearTransportFeatureTypeValue\",\"count\": 10,\"type\": \"string\",\"values\": [\"ShouldersEtc\",\"Sidewalks\",\"barrierAlongTrack\",\"bridge\",\"hangingFootbridge\",\"lineStairs\",\"overpass\",\"platform\",\"tunnel\",\"underpass\"]}]},{\"layer\": \"AsigPointCartographicFeature\",\"count\": 828,\"geometry\": \"Point\",\"attributeCount\": 2,\"attributes\": [{\"attribute\": \"AsigPointCartographicFeatureTypeValue\",\"count\": 10,\"type\": \"string\",\"values\": [\"centralTelephone\",\"monitoringStation\",\"monument\",\"parking\",\"petrolStation\",\"prominetDeciduousTree\",\"sunkenRock\",\"telephoneCabin\",\"waterPurifier\",\"weatherStation\"]},{\"attribute\": \"GeographicalName\",\"count\": 50,\"type\": \"string\",\"values\": [\"\\\"Mujo Ulqinaku\\\" Hero I Popullit\",\"\\\"Reja\\\"\",\"\\\"Sabri Tuçi\\\" Skulptor I Merituar\",\"Abdyl Frashëri\",\"Aleks Buda\",\"Andon Z.Çajupi\",\"Avni Rustemi\",\"Azem Hajdari\",\"Banjë Publike Mesdhetare\",\"Baraka e Nushajve\",\"Bazilika e \\\"Shen Mehillit\\\" Arapaj\",\"BeachMonitoringStation\",\"Busti \\\"Dedë Gjon Luli\\\"\",\"Busti \\\"Hasan Prishtina\\\"\",\"Busti \\\"Osman Kazazi\\\"\",\"Busti Heronjtë e Popullit \\\"Vojo Kushi\\\" , \\\"Sadik Stavaleci\\\" , \\\"Xhorxhi Martini\\\"\",\"Eqerem Çabej\",\"Fan Noli\",\"Fan S.Noli\",\"Françesk Radi\",\"Frederik Shopen\",\"Friendship Monument\",\"Grupi i Fëmijëve Antifashistë të Tiranës Debatik\",\"Heroi i Popullit \\\"Vojo Kushi\\\"\",\"Ismail Qemal Vlora\",\"Jeronim De Rada\",\"Kulla e Sahatit\",\"Mbreti Zog I\",\"Medreseja e Tiranës (Haxhi Mahmut Dashi)\",\"Monumenti \\\" Skënderbe\\\"\",\"Monumenti \\\"Adem Jashari\\\"\",\"Monumenti \\\"Nënë Tereza\\\"\",\"Monumenti i \\\" Pavarësisë \\\"\",\"Mosaic of Tirana\",\"Naim Frashëri\",\"NoiseMonitoringStation\",\"Papa Françesku\",\"PollutionMonitoringStation\",\"Pusi i Top Hanes\",\"Pylli i Dritëroit\",\"Qemal Stafa\",\"RiverMonitoringStation\",\"Sabri Godo\",\"Sami Frashëri\",\"Sarah i \\\"Selim Pashë Toptanit\\\"-Selamllëku\",\"Sulejman Pasha\",\"Thomas Woodrows Wilson\",\"Ushtari i Panjohur\",\"Varr Monumental\",\"Varreza e Ushtarëve Gjermanë\"]}]},{\"layer\": \"AsigPointReligiousFeature\",\"count\": 306,\"geometry\": \"Point\",\"attributeCount\": 2,\"attributes\": [{\"attribute\": \"AsigPointReligiousFeatureTypeValue\",\"count\": 9,\"type\": \"string\",\"values\": [\"belfry\",\"cathedral\",\"chapel\",\"church\",\"largeMosque\",\"mixedCemetery\",\"mosque\",\"muslimCemetery\",\"solidaryGrave\"]},{\"attribute\": \"GeographicalName\",\"count\": 10,\"type\": \"string\",\"values\": [\"Kisha Adventiste\",\"Kisha Katolike e Shën Luçisë\",\"Kisha e Shën Gjergjit\",\"Medreseja \\\"Mustafa Varoshi\\\"\",\"Missionaries Of Charity Motrat e Nënë Terezës\",\"Myftinia Durrës\",\"Qendra Kulturore e Fëmijeve\",\"Shën Pavli\",\"Xhamia \\\"Fati\\\"\",\"Xhamia e Re Durrës\"]}]},{\"layer\": \"Beacon\",\"count\": 18,\"geometry\": \"Point\",\"attributeCount\": 0,\"attributes\": []},{\"layer\": \"BreakLine\",\"count\": 320,\"geometry\": \"LineString\",\"attributeCount\": 1,\"attributes\": [{\"attribute\": \"BreakLineTypevalue\",\"count\": 1,\"type\": \"string\",\"values\": [\"flatAreaBoundary\"]}]},{\"layer\": \"Building\",\"count\": 210856,\"geometry\": \"Polygon\",\"attributeCount\": 3,\"attributes\": [{\"attribute\": \"Building\",\"count\": 5,\"type\": \"string\",\"values\": [\"administrativeBuilding\",\"building\",\"educationalBuilding\",\"religiousBuilding\",\"serviceBuilding\"]},{\"attribute\": \"GeographicalName\",\"count\": 561,\"type\": \"string\",\"values\": [\" \",\" Viktoria\",\"\\\"Albanian College\\\" Durrës\",\"\\\"Autoriteti Kombëtar i Ushqimit\\\"\",\"\\\"Sani Service Centrali\\\" Trauma Center\",\"AAC\",\"AK / AKM / AKUK\",\"AKBN\",\"AKBPM\",\"AKEP\",\"AKSEM\",\"ALUIZNI\",\"APR\",\"ASPA\",\"ATP\",\"Administrata Spitalore\",\"Adorions Palace\",\"Akademia e Filmit Marubi\",\"Akademina e Shkencave\",\"Albanian University\",\"Albcontrol\",\"Alta Group\",\"Amb. Britanike\",\"Amb. Bullgare\",\"Amb. Franceze\",\"Amb. Gjermane\",\"Amb. Greke\",\"Amb. Iraniane\",\"Amb. Italiane\",\"Amb. Kineze\",\"Amb. Rumune\",\"Amb. Ruse\",\"Amb. Shtetit të Palestinës\",\"Amb. Spanjolle\",\"Amb. Suedeze\",\"Amb. Çeke\",\"Ambasada Austriake\",\"Ambasada Hollandeze\",\"Ambulanca \\\"Arapaj 2\\\"\",\"Ambulanca Frutikulturë\",\"Ambulanca Guzaj\",\"Ambulanca Karpen\",\"Ambulanca Koxhas-fushë\",\"Ambulanca Koxhas-kodër\",\"Ambulanca Laknas\",\"Ambulanca Lanabregas\",\"Ambulanca Mullet\",\"Ambulanca Qereke\",\"Ambulanca Qesarakë\",\"Ambulanca Rinas\",\"Ambulanca Tapizë\",\"Ambulanca Valias i Ri\",\"Ambulanca Valias i Vjetër\",\"Ambulanca Vlashaj\",\"American Eye Center\",\"Arkivi Qendror ISSH\",\"Arkivi Qëndror Shtetëror i Filmit\",\"Arkivi Shtetëror i Sistemit\",\"Asema Academy\",\"Autoservis \\\"I.Bardhoshi\\\"\",\"Banka Kombëtare Tregtare\",\"Bashkia Shijak\",\"Bashkia Vorë\",\"Bashkësia e Vëllazërisë së Tarikatit Rrifai,Selia Kombëtare,Tiranë\",\"Biblioteka \\\"Petro Zheji\\\" / Qendra Shëndetësore Nr.4\",\"Biblioteka, Qendra Shpresë\",\"Bibloteka Kombëtare\",\"Bunk'Art\",\"Bunk'Art 2\",\"Church of God,The Redeemed Christian \\\"Kisha Shpëtimtare\\\"\",\"Classic \",\"Departamenti i Prodhimit Shtazor i Akuakulturës dhe Peshkimit, Fakulteti i Bujqësisë dhe Mjedisit, Univ. Bujqësor i Tiranës\",\"Diagnostic\",\"Diagnostic Center \\\"Erton\\\"\",\"Dogana\",\"Drejtoria Arsimore Rajonale , Tiranë\",\"Drejtoria Bujqësisë Tiranë\",\"Drejtoria Rajonale e Formimit Profesional Nr.4\",\"Drejtoria Rajonale e Rrugëve\",\"Drejtoria Rajonale e Shërbimit të Transportit Rrugor Tiranë\",\"Drejtoria e Administrimit të Pyjeve dhe Kullotave\",\"Drejtoria e Burgjeve\",\"Drejtoria e Investimeve të Punëve Publike\",\"Drejtoria e Policisë\",\"Drejtoria e Përgjithshme e Burgjeve\",\"Drejtoria e Përgjithshme e Metrologjisë\",\"Drejtoria e Përgjithshme e Policisë së Shtetit\",\"Drejtoria e Përgjithshme e Standartizimit\",\"Drejtoria e Përgjithshme e Tatimeve\",\"Drejtoria e Përgjithshme e Transportit Rrugor\",\"Drejtoria e Përgjithëshme e Taksave dhe Tarifave Vendore\",\"Drejtoria e Qarkut Tiranë,Min. e Bujqësisë Zhvillimit Rural dhe Administrimit të Ujërave\",\"Drejtoria e Shërbimeve Mbështetëse / Godina Nr. 17\",\"Dëshmitarët e Jehovait\",\"ERE\",\"Eurosig\",\"FSHZH\",\"Fakulteti Farmacisë\",\"Fakulteti i Bioteknologjisë dhe Ushqimit, Univ. Bujqësor i Tiranës\",\"Fakulteti i Bujqësisë dhe Mjedisit, Univ. Bujqësor i Tiranës\"]},{\"attribute\": \"sarea\",\"count\": 1000,\"type\": \"number\",\"values\": [0.38547840022500459,0.4278715799830277,0.5332484405223703,0.5381718800878999,0.5939885602625706,0.6030247593108916,0.6040961790840772,0.6322888399373329,0.633594139532548,0.6336494798338492,0.637321780464494,0.6443049000934348,0.6478908408927804,0.6495638996653691,0.6502019795193229,0.6506335800723639,0.6548223598523209,0.6570144001602516,0.6594114648687074,0.6715666799891514,0.6725315395459264,0.6813135602234551,0.6881289199119899,0.6884166795848643,0.6928868001903191,0.6944732396090498,0.6963214402459501,0.7099604802341055,0.7112800201911884,0.7127747201969016,0.7228522395649126,0.7302699000952788,0.7340521605708266,0.7344835999843791,0.7361444805468139,0.7395423596330316,0.7493507198974366,0.75708910018325,0.7611606983238675,0.7635188206014898,0.7695286396970607,0.7765240400164863,0.7785444800455761,0.7906294000617922,0.8104706396117365,0.8121175210810672,0.8144370395085206,0.8176395599714876,0.8299308004391574,0.8306258601111651,0.8364684206156078,0.8375215700448084,0.8386983210592198,0.8537659580347957,0.8591261799545471,0.8696823195377814,0.8709017400505266,0.8729502600329238,0.8900474404032057,0.8921901610500629,0.8927202203896072,0.8933747207963008,0.9001489996578768,0.9008243791993995,0.9010948394158965,0.9080120199641917,0.9093785806051177,0.9141001399821086,0.9143697605814392,0.9196818800198389,0.9236022794782568,0.9256519998749271,0.9321206602241063,0.9324666000638359,0.9340669185498152,0.9344263198856193,0.9365415009027385,0.9366450191099974,0.9370176003967389,0.9377434804959154,0.9416291604760216,0.9452921714490111,0.960356279992727,0.9605450152810129,0.9628633394887372,0.9650575996765286,0.9711627997547879,0.9721139992347583,0.9732130800224302,0.977277639025063,0.9793595800761377,0.9812965699106513,0.9840125809668137,0.9875746812184189,0.9900341995879255,0.9979041996245639,0.9984591592363008,0.9990567993137024,0.9992951610433201,0.9993862804053586],\"min\": 0.38547840022500459,\"max\": 26033.243419901613}]},{\"layer\": \"BuildingPart\",\"count\": 80957,\"geometry\": \"Polygon\",\"attributeCount\": 3,\"attributes\": [{\"attribute\": \"BuildingPart\",\"count\": 5,\"type\": \"string\",\"values\": [\"administrativeBuildingPart\",\"buildingPart\",\"educationalBuildingPart\",\"religiousBuildingPart\",\"serviceBuildingPart\"]},{\"attribute\": \"GeographicalName\",\"count\": 704,\"type\": \"string\",\"values\": [\"\\\"Blue Star\\\"\",\"\\\"Bordi i Kullimit Durrës-Krujë\\\"\",\"\\\"Drejtoria e Bujqësisë'' Durrës\",\"\\\"Ndërmarrja Rruga Durrës\\\"\",\"\\\"Top School\\\"\",\"'Bashkia'' Durrës\",\"'Drejtoria Rajonale Tatimore'' Durrës\",\"'Drejtoria e Përgjithshme e Hekurudhave'' Durrës\",\"'Institucioni i Ekzekutimit të Vendimeve Penale'' Durrës\",\"'Myftinia'' Durrës\",\"'Xhamia e Re'' Durrës\",\"'Zyra Përparimbore'' Durrës\",\"'Zyra e Punës'' Durrës\",\"AKT / AKB\",\"AKU\",\"ALEAT Shpk\",\"ALUIZNI\",\"AMSCA\",\"AQTN\",\"ARZH\",\"ASA\",\"ASHP\",\"ASHR\",\"ASIG / AKSHI\",\"AZHT\",\"Agjencia Funerale Shtetërore\",\"Agjencia Kombëtare e Arsimit, Instituti i Zhvillimit të Arsimit\",\"Agjencia Kombëtare e Duhan-Cigareve\",\"Agjencia e Abonimit të Shtypit\",\"Agjencia e Pagesës / ISHTI\",\"Agjencia për Zhvillim Ekonomik Rajonal\",\"Air control\",\"Akademia e Arteve\",\"Akademia e Sigurisë\",\"Albanian College Tirana\",\"Albanian International School\",\"Albanian University\",\"Albanian University, Fakulteti i Arkitekturës dhe Inxhinierive\",\"Albtelecom\",\"Alpha Bank\",\"Aluizni, Drejtoritë Rajonale Tiranë\",\"Amb. Brazilit / Amb. Malit të Zi / European Bank / Shoqata e Miqesise Shqiperi-Rusi / Tore Drin\",\"Amb. Japoneze\",\"Amb. Kosovës\",\"Amb. Mbretërisë  së  Vendeve të  Ulta\",\"Amb. Polake\",\"Amb. Selisë së Shenjtë\",\"Amb. Serbisë\",\"Amb. Shteteve të Bashkuara të Amerikës\",\"Amb. Shtetit të Katarrit\",\"Amb. Sllovene\",\"Amb. Turke\",\"Amb. Zviceriane\",\"Ambasada Arabisë Saudite\",\"Ambulanca \\\"Sukth\\\"\",\"Ambulanca Mjull Bathore\",\"American Bank of Investments\",\"American Medical Center\",\"Arena Sportive \\\"Dhimitër Goga\\\"\",\"Arqipeshkvia Metropolitane Tiranë-Durrës\",\"Arsakeio\",\"Artikuj Bujqësor & Blektoral\",\"Auditorium \\\"Galileu Galiei\\\"\",\"Autoriteti Portual Durrës\",\"Autoriteti i Mbikëqyrjes Financiare / ATK\",\"Avokati i Popullit\",\"Avokatura e Shtetit\",\"Banka Kombëtare Tregtare\",\"Banka e Shqipërisë\",\"Bashkia Kamëz\",\"Bashkia Tiranë\",\"Biblioteka \\\"Musinë Kokalari\\\"\",\"Biblioteka Kombëtare\",\"Biblioteka Qyteti Studenti\",\"Biblioteka Shkencore\",\"Cerdhja Nr.8, Pranverat\",\"Credins Bank\",\"Dega e Doganës Rinas / Tirana International Airport \\\"Nënë Tereza\\\",Godina e Administratës / Albcontrol / Marubi Lounge\",\"Departamenti i Stacionit Transmetues Tokësor\",\"Deutsch-Albanische Schule\",\"Dhoma Kombëtare e Përmbarimit Gjyqësorë Penal,Studio Përmbarimore I.D.C\",\"Dhoma e Tregtisë dhe Industrisë\",\"Dispanseria / Qendër Shëndetësore\",\"Drejtoria Arsimore Durrës\",\"Drejtoria Rajonale E Fondit Të Sigurimit Të Detyrueshëm Të Kujdesit Shëndetësor Durrës\",\"Drejtoria Rajonale Kamëz-Vorë\",\"Drejtoria Rajonale e Fondit të Sigurimit të Detyrueshëm të Kujdesit Shëndetësor Durrës\",\"Drejtoria Rajonale e Formimit Profesional Publik Nr.1, Tiranë\",\"Drejtoria Rajonale e Rezervave\",\"Drejtoria Rajonale e Shëndetësisë\",\"Drejtoria Rajonale e Shërbimit të Transportit Rrugor, Tiranë\",\"Drejtoria Rajonale e Sigurimeve Shoqërore Tiranë\",\"Drejtoria Rajonale e Sigurimit dhe Kujdesit Shëndetësor\",\"Drejtoria Transportit dhe Ofiçina\",\"Drejtoria e Antiterrorit\",\"Drejtoria e Higjenës dhe Epidemiologjisë\",\"Drejtoria e Konvikteve Shkollave të Mesme\",\"Drejtoria e Objekteve në Bashkëpronësi dhe Administrimit të Njësive Administrative / Njësia Administrative Nr.10\",\"Drejtoria e Planifikimit të Punëve Publike Bashkia Tiranë\",\"Drejtoria e Policisë\"]},{\"attribute\": \"sarea\",\"count\": 1000,\"type\": \"number\",\"values\": [0.6511173590736794,0.8382909005451933,0.877392921217544,1.049458109981201,1.0679618559601963,1.0871485994770225,1.1125076799569576,1.132118983866853,1.1465866799248344,1.202688419992311,1.2456346109412345,1.25832896216314,1.2702718598682688,1.290066480175723,1.3314077089623427,1.3319443788923798,1.3762006410632586,1.3793341801278814,1.4317938599664713,1.433408636565087,1.4447490395821175,1.4468424409057848,1.4525658841545002,1.4561365309010906,1.4602018397342823,1.4710569804069294,1.5041854397687665,1.5290639404967182,1.5375298213958817,1.5845728800817086,1.5952174402038002,1.6121678408184646,1.619465160037529,1.6332322600150087,1.6342001301519694,1.636641498013217,1.6555538117587106,1.6634812394268515,1.6671214392682477,1.6712509996472634,1.671582579771219,1.6764456006769329,1.6802060109720918,1.683014900674785,1.6881000408994287,1.6887672199876894,1.6909729598726342,1.7012422702184873,1.7185256894074766,1.7196144090670776,1.7548952395046898,1.755589657398742,1.7604796819637195,1.7621114004079313,1.7629897599158602,1.7717748399570508,1.779891840467494,1.8134183180380466,1.8196175212659347,1.8202804208945614,1.8225200603892194,1.831650950406927,1.8368414176987949,1.8393023997442076,1.8396982006179943,1.8451345811511169,1.845400540567669,1.8505783895349284,1.8507770408343794,1.8576297217887275,1.8585402586229292,1.8640500874672419,1.8691700792263953,1.8693450679093529,1.874740178564574,1.8888456697590169,1.926254081043003,1.9390059999431074,1.941948120312606,1.942033918570103,1.9688722799658416,1.9750253995476948,1.9908755200948115,1.9931847617996837,10.001008341884788,10.00173712064381,10.002419497959718,10.002812160682092,10.003109928684996,10.003986270647815,10.00950048692591,10.010053259463286,10.011619618014724,10.011699280105077,10.011882837615442,10.012122440761765,10.012327166276556,10.012831333025487,10.017861355298273,10.019176557745741],\"min\": 0.6511173590736794,\"max\": 22179.535365871638}]},{\"layer\": \"Cabinet\",\"count\": 6,\"geometry\": \"Point\",\"attributeCount\": 0,\"attributes\": []},{\"layer\": \"CablewayLink\",\"count\": 8,\"geometry\": \"LineString\",\"attributeCount\": 2,\"attributes\": [{\"attribute\": \"AsigCablewayPurposeValue\",\"count\": 1,\"type\": \"string\",\"values\": [\"cablecarForTravel\"]},{\"attribute\": \"CablewayTypevalue\",\"count\": 1,\"type\": \"string\",\"values\": [\"cabinCableCar\"]}]},{\"layer\": \"CablewayNode\",\"count\": 1,\"geometry\": \"Point\",\"attributeCount\": 1,\"attributes\": [{\"attribute\": \"AsigCablewayNodePurposeValue\",\"count\": 1,\"type\": \"string\",\"values\": [\"cablecarForTravel\"]}]},{\"layer\": \"ContourLine\",\"count\": 177677,\"geometry\": \"LineString\",\"attributeCount\": 2,\"attributes\": [{\"attribute\": \"ContourLineTypeValue\",\"count\": 3,\"type\": \"string\",\"values\": [\"auxility(0.5m)\",\"master(5m)\",\"ordinary(1m)\"]},{\"attribute\": \"HeightValue\",\"count\": 645,\"type\": \"number\",\"values\": [-0.5,-1,-1.5,-2,-2.5,0,0.5,1,1.5,10,10.5,100,100.5,101,101.5,102,102.5,103,103.5,104,104.5,105,105.5,106,106.5,107,107.5,108,108.5,109,109.5,11,11.5,110,110.5,111,111.5,112,112.5,113,113.5,114,114.5,115,115.5,116,116.5,117,117.5,118,118.5,119,119.5,12,12.5,120,120.5,121,121.5,122,122.5,123,123.5,124,124.5,125,125.5,126,126.5,127,127.5,128,128.5,129,129.5,13,13.5,130,130.5,131,131.5,132,132.5,133,133.5,134,134.5,135,135.5,136,136.5,137,137.5,138,138.5,139,139.5,14,14.5,140],\"min\": -2.5,\"max\": 498}]},{\"layer\": \"CrossingA\",\"count\": 14974,\"geometry\": \"Polygon\",\"attributeCount\": 1,\"attributes\": [{\"attribute\": \"CrossingTypevalue\",\"count\": 4,\"type\": \"string\",\"values\": [\"aqueduct\",\"bridge\",\"culvert\",\"siphon\"]}]},{\"layer\": \"CrossingL\",\"count\": 8377,\"geometry\": \"LineString\",\"attributeCount\": 1,\"attributes\": [{\"attribute\": \"CrossingTypevalue\",\"count\": 3,\"type\": \"string\",\"values\": [\"aqueduct\",\"culvert\",\"siphon\"]}]},{\"layer\": \"DamOrWeir\",\"count\": 336,\"geometry\": \"Polygon\",\"attributeCount\": 0,\"attributes\": []},{\"layer\": \"DrainageBasin\",\"count\": 4467,\"geometry\": \"Polygon\",\"attributeCount\": 0,\"attributes\": []},{\"layer\": \"Duct\",\"count\": 2,\"geometry\": \"LineString\",\"attributeCount\": 1,\"attributes\": [{\"attribute\": \"UtilityDeliveryTypeValue\",\"count\": 1,\"type\": \"string\",\"values\": [\"collection\"]}]},{\"layer\": \"ElevationGridCoverage\",\"count\": 4396,\"geometry\": \"Point\",\"attributeCount\": 2,\"attributes\": [{\"attribute\": \"ElevationPropertyTypeValue\",\"count\": 1,\"type\": \"string\",\"values\": [\"height\"]},{\"attribute\": \"SurfaceTypeValue\",\"count\": 1,\"type\": \"string\",\"values\": [\"DTM\"]}]},{\"layer\": \"Embankment\",\"count\": 1022,\"geometry\": \"LineString\",\"attributeCount\": 0,\"attributes\": []},{\"layer\": \"EnvironmentalManagementFacilityA\",\"count\": 7,\"geometry\": \"Polygon\",\"attributeCount\": 1,\"attributes\": [{\"attribute\": \"EnvironmentalManagementFacilityTypeValue\",\"count\": 1,\"type\": \"string\",\"values\": [\"site\"]}]},{\"layer\": \"EnvironmentalManagementFacilityP\",\"count\": 16,\"geometry\": \"Point\",\"attributeCount\": 1,\"attributes\": [{\"attribute\": \"EnvironmentalManagementFacilityTypeValue\",\"count\": 1,\"type\": \"string\",\"values\": [\"facility\"]}]},{\"layer\": \"FallsA\",\"count\": 12,\"geometry\": \"Polygon\",\"attributeCount\": 2,\"attributes\": [{\"attribute\": \"AsigFallTypevalue\",\"count\": 2,\"type\": \"string\",\"values\": [\"cascade\",\"fall\"]},{\"attribute\": \"fall\",\"count\": 1,\"type\": \"string\",\"values\": [\" \"]}]},{\"layer\": \"Ford\",\"count\": 89,\"geometry\": \"Polygon\",\"attributeCount\": 0,\"attributes\": []},{\"layer\": \"GovernmentalService\",\"count\": 946,\"geometry\": \"Point\",\"attributeCount\": 2,\"attributes\": [{\"attribute\": \"GeographicalName\",\"count\": 69,\"type\": \"string\",\"values\": [\"\\\"Drejtoria e Bujqësisë Durrës \\\"\",\"\\\"Top School\\\"\",\"Administrata Spitalore\",\"Albanian College\\\" Durrës\",\"Ambulanca \\\"Arapaj 2\\\"\",\"Autoriteti Portual Durrës\",\"Bashkia Durrës\",\"Drejtoria Arsimore Durrës\",\"Drejtoria Rajonale E Shendetesise\",\"Drejtoria Rajonale Tatimore Durrës\",\"Drejtoria Rajonale e Fondit të Sigurimit të Detyrueshëm të Kujdesit Shëndetësor Durrës\",\"Drejtoria e Higjenës dhe Epidemiologjisë\",\"Drejtoria e Policisë\",\"Drejtoria e Përgjithshme e Doganave\",\"Drejtoria e Përgjithshme e Hekurudhave Durrës\",\"Educational Complex \\\"Kasa\\\".\",\"Fakulteti i Studimeve të Integruara me Praktikën \\\"Fastip\\\"\",\"Gjimnazi \\\"Gjergj Kastrioti\\\"\",\"Gjimnazi \\\"Leonik Tomeo\\\"\",\"Gjimnazi \\\"Naim Frashëri\\\"\",\"Gjimnazi \\\"Olsi Lasko\\\"\",\"Gjykata e Durrësit\",\"Institucioni i Ekzekutimit të Vendimeve Penale Durrës\",\"Kolegji \\\"Eneida\\\"\",\"Kolegji \\\"Turgut Ozal\\\"\",\"Njësia Administrative Nr.1\",\"Njësia Administrative Nr.3\",\"Njësia Administrative Nr.4\",\"Policia Bashkiake\",\"Posta Shqiptare\",\"Posta shqiptare\",\"Prefektura e Qarkut Durrës\",\"Qendra Kulturore e Fëmijeve\",\"Qëndra Shëndetësore\",\"Qëndra Shëndetësore Nr.4\",\"Qëndra Shëndetësore Verore\",\"Qëndra Social Kulturore \\\"Selim Gashi\\\"\",\"Shk. \\\"Demokracia\\\"\",\"Shk. \\\"Hajdar Dushi\\\"\",\"Shk. \\\"Hysen Cela\\\"\",\"Shk. \\\"Ibrahim Kodra\\\"\",\"Shk. \\\"Kushtrimi I Lirisë\\\"\",\"Shk. \\\"Marie Kaculini\\\"\",\"Shk. \\\"Met Hasa\\\"\",\"Shk. \\\"Myslim Hida\\\"\",\"Shk. \\\"Nënë Tereza \\\"\",\"Shk. \\\"Qemal Mici\\\"\",\"Shk. \\\"Shaqe Mazreku\\\"\",\"Shk. 12 Vjeçare&Artistike \\\"Talenti\\\"\",\"Shk. 9 Vjeçare \\\"14 Nëntori\\\"\",\"Shk. 9 Vjeçare \\\"Abedin Dino\",\"Shk. 9 Vjeçare \\\"Bajram Curri\\\"\",\"Shk. 9 Vjeçare \\\"Bedrie Bebeziqi\\\"\",\"Shk. 9 Vjeçare \\\"Jusuf Puka\\\"\",\"Shk. 9 Vjeçare \\\"Vasil Ziu\\\"\\\"\",\"Shk. 9 Vjeçare \\\"Vëllezërit Haradinaj\\\"\",\"Shk. 9-Vjeçare\\\"Hasan KoçI\\\"\",\"Shk. Speciale E Fëmijeve Me Aftësi Te Kufizuar\",\"Shk. e Mesme Artistike \\\"Jan Kukuzeli\\\"\",\"Shk. e Mesme Jopublike \\\"Konica\\\"\",\"Shk. e Mesme Kombëtare Sportive \\\"Benardina Qerraxhia\\\"\",\"Shk. e Mesme Profesionale\\\"Beqir Çela\\\"\",\"Shk.\\\"Myslim Hida\\\"\",\"Shk.12 Vjeçare Jopublike\\\"Hafiz Ali Podgorica\\\"\",\"Spitali \\\"Durrës\\\"\",\"UKD\",\"Univ. \\\"Aleksandër Moisiu\\\" Durrës\",\"Zyra Përmbarimore Durrës\",\"Zyra e Punës Durrës\"]},{\"attribute\": \"ServiceTypeList\",\"count\": 27,\"type\": \"string\",\"values\": [\" \",\"administrationForPublicOrderAndSafety\",\"bachelorOrEquivalentEducation\",\"charityAndCounselling\",\"childCareService\",\"defence\",\"earlyChildhoodEducation\",\"education\",\"environmentalProtection\",\"fireStation\",\"generalAdministrationOffice\",\"generalHospital\",\"generalMedicalService\",\"health\",\"hospitalService\",\"housing\",\"lowerSecondaryEducation\",\"masterOrEquivalentEducation\",\"outpatientService\",\"policeService\",\"primaryEducation\",\"publicAdministrationOffice\",\"rescueHelicopterLandingSite\",\"rescueStation\",\"socialService\",\"specializedHospital\",\"upperSecondaryEducation\"]}]},{\"layer\": \"HydroNode\",\"count\": 3357,\"geometry\": \"Point\",\"attributeCount\": 1,\"attributes\": [{\"attribute\": \"HydroNodeCategoryValue\",\"count\": 6,\"type\": \"string\",\"values\": [\"boundary\",\"flowConstriction\",\"flowRegulation\",\"junction\",\"outlet\",\"source\"]}]},{\"layer\": \"InstallationPart\",\"count\": 3,\"geometry\": \"Point\",\"attributeCount\": 1,\"attributes\": [{\"attribute\": \"InstallationPartValue\",\"count\": 1,\"type\": \"string\",\"values\": [\"waterPump\"]}]},{\"layer\": \"LandCoverUnit\",\"count\": 81316,\"geometry\": \"Polygon\",\"attributeCount\": 1,\"attributes\": [{\"attribute\": \"LandCoverClass\",\"count\": 32,\"type\": \"string\",\"values\": [\"111ContinuousUrbanFabric\",\"112DiscontinuousUrbanFabric\",\"121IndustrialOrCommercialUnits\",\"122RoadAndRailNetworksAndAssociatedLand\",\"124Airports\",\"131MineralExtractionSites\",\"133ConstructionSites\",\"141GreenUrbanAreas\",\"142SportAndLeisureFacilities\",\"211Non-irrigatedArableLand\",\"212PermanentlyIrrigatedLand\",\"221Vineyards\",\"222FruitTreesAndBerryPlantations\",\"223OliveGroves\",\"231Pastures\",\"241AnnualCropsAssociatedWithPermanentCrops\",\"242ComplexCultivationPatterns\",\"243LandPrincipallyOccupiedByAgricultureWithSignificantAreasOfNaturalVegetation\",\"244Agro-forestryAreas\",\"311Broad-leavedForest\",\"313MixedForest\",\"321NaturalGrasslands\",\"323SclerophyllousVegetation\",\"324TransitionalWoodland-shrub\",\"331BeachesDunesSands\",\"332BareRocks\",\"333SparselyVegetatedAreas\",\"411InlandMarshes\",\"412PeatBogs\",\"511WaterCourses\",\"512WaterBodies\",\"523SeaAndOcean\"]}]},{\"layer\": \"LandwaterBoundary\",\"count\": 27054,\"geometry\": \"LineString\",\"attributeCount\": 2,\"attributes\": [{\"attribute\": \"OriginValue\",\"count\": 2,\"type\": \"string\",\"values\": [\"manMade\",\"natural\"]},{\"attribute\": \"WaterLevelvalue\",\"count\": 2,\"type\": \"string\",\"values\": [\" \",\"highWater\"]}]},{\"layer\": \"Manhole\",\"count\": 28920,\"geometry\": \"Point\",\"attributeCount\": 0,\"attributes\": []},{\"layer\": \"NamedPlace\",\"count\": 1981,\"geometry\": \"Point\",\"attributeCount\": 2,\"attributes\": [{\"attribute\": \"GeographicalName\",\"count\": 1000,\"type\": \"string\",\"values\": [\" \\\"Tradita e vjetër Tironse\\\"\",\"\\\"Albanian College\\\" Durrës\",\"\\\"Autoriteti Kombëtar i Ushqimit\\\"\",\"\\\"Blue Star\\\"\",\"\\\"Bordi i Kullimit Durrës - Krujë\\\"\",\"\\\"Donald J. Trump\\\"\",\"\\\"Drejtoria e Bujqësisë Durrës \\\"\",\"\\\"Ecotirana\\\", Bashkia Tiranë\",\"\\\"IN\\\" TV\",\"\\\"Natyra e Qetë\\\"\",\"\\\"Ndërmarrja Rruga Durrës\\\"\",\"\\\"News 24\\\"\",\"\\\"Queen Park\\\"\",\"\\\"Sani Service Centrali\\\" Trauma Center\",\"\\\"Selman Stërmasi\\\"\",\"\\\"Top School\\\"\",\"\\\"Zogu i Zi\\\"\",\"''Gega Oil''\",\"'Drejtoria Rajonale e Fondit të Sigurimit të Detyrueshëm të Kujdesit Shëndetësor'' Durrës\",\"'Kings Education\\\"\",\"'Myftinia'' Durrës\",\"'Xhamia e Re'' Durrës\",\"'Zyra e Punës'' Durrës\",\"AAC\",\"AIR ALBANIA STADIUM\",\"AK\",\"AKB\",\"AKBN\",\"AKBPM\",\"AKEP\",\"AKM\",\"AKSEM\",\"AKSHI\",\"AKT\",\"AKU\",\"AKUK\",\"ALEAT Shpk\",\"ALUIZNI\",\"AMSCA\",\"APR\",\"AQTN\",\"ARSH\",\"ARZH\",\"ASA\",\"ASA,Muzeu Arkeologjik\",\"ASHP\",\"ASHR\",\"ASIG\",\"ASPA\",\"ATK\",\"ATP\",\"AZHT\",\"Administrata Spitalore\",\"Agjencia Funerale Shtetërore\",\"Agjencia Kombëtare e Arsimit, Instituti i Zhvillimit të Arsimit\",\"Agjencia Kombëtare e Duhan-Cigareve\",\"Agjencia e Abonimit të Shtypit\",\"Agjencia e Pagesës\",\"Agjencia për Zhvillim Ekonomik Rajonal\",\"Akacia Hills\",\"Akademia e Arteve\",\"Akademia e Filmit Marubi\",\"Akademina e Shkencave\",\"Albanian College Tirana\",\"Albanian International School\",\"Albanian University\",\"Albanian University, Fakulteti i Arkitekturës dhe Inxhinierive\",\"Albcontrol\",\"Albesol \",\"Albtelecom\",\"Aluizni, Drejtoritë Rajonale Tiranë\",\"Amb. Brazilit\",\"Amb. Britanike\",\"Amb. Bullgare\",\"Amb. Franceze\",\"Amb. Gjermane\",\"Amb. Greke\",\"Amb. Iraniane\",\"Amb. Italiane\",\"Amb. Japoneze\",\"Amb. Kineze\",\"Amb. Kosovës\",\"Amb. Mbretërisë  së  Vendeve të  Ulta\",\"Amb. Polake\",\"Amb. Rumune\",\"Amb. Ruse\",\"Amb. Selisë së Shenjtë\",\"Amb. Serbisë\",\"Amb. Shteteve të Bashkuara të Amerikës\",\"Amb. Shtetit të Katarrit\",\"Amb. Shtetit të Palestinës\",\"Amb. Sllovene\",\"Amb. Spanjolle\",\"Amb. Suedeze\",\"Amb. Turke\",\"Amb. Zviceriane\",\"Amb. e Malit të Zi\",\"Amb. Çeke\",\"Ambasada Hollandeze\",\"Ambulanca\"]},{\"attribute\": \"NamedPlaceTypeValue\",\"count\": 5,\"type\": \"string\",\"values\": [\"building\",\"hydrography\",\"landform\",\"other\",\"populatedPlace\"]}]},{\"layer\": \"OilGasChemicalsPipe\",\"count\": 64,\"geometry\": \"LineString\",\"attributeCount\": 3,\"attributes\": [{\"attribute\": \"AsigOilGasChemicalsPipeTypeValue\",\"count\": 1,\"type\": \"string\",\"values\": [\"liquefiedNaturalGas\"]},{\"attribute\": \"OilGasChemicalsProductTypeValue\",\"count\": 1,\"type\": \"string\",\"values\": [\"liquefiedNaturalGas\"]},{\"attribute\": \"UtilityDeliveryTypeValue\",\"count\": 1,\"type\": \"string\",\"values\": [\"collection\"]}]},{\"layer\": \"Order1_State_code\",\"count\": 3356,\"geometry\": \"LineString\",\"attributeCount\": 5,\"attributes\": [{\"attribute\": \"Entity\",\"count\": 1,\"type\": \"string\",\"values\": [\"2DPolyline\"]},{\"attribute\": \"FID_\",\"count\": 1,\"type\": \"number\",\"values\": [0],\"min\": 0,\"max\": 0},{\"attribute\": \"Layer\",\"count\": 4,\"type\": \"string\",\"values\": [\"Kufi Shtetëror Liqen\",\"Kufi Shtetëror Lumë\",\"Kufi Shtetëror Tokësor\",\"Vijë Bregdeti\"]},{\"attribute\": \"attrvalue\",\"count\": 1,\"type\": \"string\",\"values\": [\"1stOrder (Natioanl Boundary)\"]},{\"attribute\": \"code\",\"count\": 1,\"type\": \"string\",\"values\": [\"04-01-L-01\"]}]},{\"layer\": \"Order3_Municipal_code\",\"count\": 146826,\"geometry\": \"Polygon\",\"attributeCount\": 13,\"attributes\": [{\"attribute\": \"Autoriteti\",\"count\": 61,\"type\": \"string\",\"values\": [\"BAJRAM CURRI\",\"BALLSH\",\"BELSH\",\"BERAT\",\"BILISHT\",\"BULQIZË\",\"BURREL\",\"CËRRIK\",\"DELVINË\",\"DERMISH\",\"DIVJAKË\",\"DURRËS\",\"ELBASAN\",\"ERSEKË\",\"FIER\",\"FUSHË ARRËS\",\"GJIROKASTËR\",\"GRAMSH\",\"HIMARË\",\"KAMËZ\",\"KAVAJË\",\"KLOS\",\"KONISPOL\",\"KOPLIK\",\"KORÇË\",\"KRUJË\",\"KRUMË\",\"KUKËS\",\"KUÇOVË\",\"KËLCYRË\",\"LAÇ\",\"LEZHË\",\"LIBOHOVË\",\"LIBRAZHD\",\"LUSHNJE\",\"MALIQ\",\"MEMALIAJ\",\"PATOS\",\"PEQIN\",\"PESHKOPI\",\"POGRADEC\",\"POLIÇAN\",\"PRRENJAS\",\"PUKË\",\"PUSTEC\",\"PËRMET\",\"ROSKOVEC\",\"RROGOZHINË\",\"RRËSHEN\",\"SARANDË\",\"SELENICË\",\"SHIJAK\",\"SHKODËR\",\"SOFRATIKË\",\"TEPELENË\",\"TIRANË\",\"URA VAJGURORE\",\"VAU I DEJËS\",\"VLORË\",\"VORË\",\"ÇOROVODË\"]},{\"attribute\": \"Emertim\",\"count\": 1,\"type\": \"string\",\"values\": [\"BASHKIA\"]},{\"attribute\": \"Emertimi\",\"count\": 61,\"type\": \"string\",\"values\": [\"BELSH\",\"BERAT\",\"BULQIZË\",\"CËRRIK\",\"DELVINË\",\"DEVOLL\",\"DIBËR\",\"DIVJAKË\",\"DROPULL\",\"DURRËS\",\"ELBASAN\",\"FIER\",\"FINIQ\",\"FUSHË ARRËS\",\"GJIROKASTËR\",\"GRAMSH\",\"HAS\",\"HIMARË\",\"KAMËZ\",\"KAVAJË\",\"KLOS\",\"KOLONJË\",\"KONISPOL\",\"KORÇË\",\"KRUJË\",\"KUKËS\",\"KURBIN\",\"KUÇOVË\",\"KËLCYRË\",\"LEZHË\",\"LIBOHOVË\",\"LIBRAZHD\",\"LUSHNJE\",\"MALIQ\",\"MALLAKASTËR\",\"MALËSI E MADHE\",\"MAT\",\"MEMALIAJ\",\"MIRDITË\",\"PATOS\",\"PEQIN\",\"POGRADEC\",\"POLIÇAN\",\"PRRENJAS\",\"PUKË\",\"PUSTEC\",\"PËRMET\",\"ROSKOVEC\",\"RROGOZHINË\",\"SARANDË\",\"SELENICË\",\"SHIJAK\",\"SHKODËR\",\"SKRAPAR\",\"TEPELENË\",\"TIRANË\",\"TROPOJË\",\"URA VAJGURORE\",\"VAU I DEJËS\",\"VLORË\",\"VORË\"]},{\"attribute\": \"Fillimi_I_\",\"count\": 1,\"type\": \"string\",\"values\": [\"2016/12/21 00:00:00\"]},{\"attribute\": \"ID_Alterna\",\"count\": 61,\"type\": \"number\",\"values\": [10101,10102,10103,10104,10105,10206,10207,10208,10209,10310,10311,10312,10413,10414,10415,10416,10417,10418,10419,10520,10521,10522,10523,10524,10525,10626,10627,10628,10629,10630,10631,10632,10733,10734,10735,10736,10737,10738,10839,10840,10841,10942,10943,10944,11045,11046,11047,11048,11049,11150,11151,11152,11153,11154,11255,11256,11257,11258,11259,11260,11261],\"min\": 10101,\"max\": 11261},{\"attribute\": \"Inspire_ID\",\"count\": 61,\"type\": \"string\",\"values\": [\"ASIG_ADM3_10101\",\"ASIG_ADM3_10102\",\"ASIG_ADM3_10103\",\"ASIG_ADM3_10104\",\"ASIG_ADM3_10105\",\"ASIG_ADM3_10206\",\"ASIG_ADM3_10207\",\"ASIG_ADM3_10208\",\"ASIG_ADM3_10209\",\"ASIG_ADM3_10310\",\"ASIG_ADM3_10311\",\"ASIG_ADM3_10312\",\"ASIG_ADM3_10413\",\"ASIG_ADM3_10414\",\"ASIG_ADM3_10415\",\"ASIG_ADM3_10416\",\"ASIG_ADM3_10417\",\"ASIG_ADM3_10418\",\"ASIG_ADM3_10419\",\"ASIG_ADM3_10520\",\"ASIG_ADM3_10521\",\"ASIG_ADM3_10522\",\"ASIG_ADM3_10523\",\"ASIG_ADM3_10524\",\"ASIG_ADM3_10525\",\"ASIG_ADM3_10626\",\"ASIG_ADM3_10627\",\"ASIG_ADM3_10628\",\"ASIG_ADM3_10629\",\"ASIG_ADM3_10630\",\"ASIG_ADM3_10631\",\"ASIG_ADM3_10632\",\"ASIG_ADM3_10733\",\"ASIG_ADM3_10734\",\"ASIG_ADM3_10735\",\"ASIG_ADM3_10736\",\"ASIG_ADM3_10737\",\"ASIG_ADM3_10738\",\"ASIG_ADM3_10839\",\"ASIG_ADM3_10840\",\"ASIG_ADM3_10841\",\"ASIG_ADM3_10942\",\"ASIG_ADM3_10943\",\"ASIG_ADM3_10944\",\"ASIG_ADM3_11045\",\"ASIG_ADM3_11046\",\"ASIG_ADM3_11047\",\"ASIG_ADM3_11048\",\"ASIG_ADM3_11049\",\"ASIG_ADM3_11150\",\"ASIG_ADM3_11151\",\"ASIG_ADM3_11152\",\"ASIG_ADM3_11153\",\"ASIG_ADM3_11154\",\"ASIG_ADM3_11255\",\"ASIG_ADM3_11256\",\"ASIG_ADM3_11257\",\"ASIG_ADM3_11258\",\"ASIG_ADM3_11259\",\"ASIG_ADM3_11260\",\"ASIG_ADM3_11261\"]},{\"attribute\": \"Kodi_Komb\",\"count\": 1,\"type\": \"string\",\"values\": [\"AL\"]},{\"attribute\": \"Niveli_Nac\",\"count\": 1,\"type\": \"string\",\"values\": [\"Rendi3\"]},{\"attribute\": \"Shape_Leng\",\"count\": 61,\"type\": \"number\",\"values\": [100762.088069,100871.415505,101966.686732,105923.264454,109822.087427,110903.503075,111204.387776,116627.72978,116898.078451,124346.188414,126357.081045,132110.753718,137034.354263,137058.835348,138704.39878,139794.967854,139891.77952,141008.160244,141315.21925,141430.783277,143449.732791,147663.47654,148921.18139,149601.027602,152334.080419,156243.83162,166844.655343,167275.035471,171412.778449,172123.775492,173938.268086,176082.117455,177976.667981,178010.839732,179976.38445,183021.782468,190195.842014,198484.149955,200091.764957,211762.234788,230901.854082,245067.705855,255672.284317,43330.755855,64009.6489273,68060.3042124,72045.6799889,74341.9003566,76172.4325292,77547.2167487,78383.2881356,83593.0064624,86246.1613778,87342.7988563,91223.2827852,91692.9220616,92043.1780721,96418.3082069,98534.4402613,98843.2263485,99497.2921797],\"min\": 43330.755855,\"max\": 255672.284317},{\"attribute\": \"Shteti\",\"count\": 1,\"type\": \"string\",\"values\": [\"ALB\"]},{\"attribute\": \"attrvalue\",\"count\": 1,\"type\": \"string\",\"values\": [\"3rdOrder (Municipality Boundary)\"]},{\"attribute\": \"code\",\"count\": 1,\"type\": \"string\",\"values\": [\"04-01-L-03\"]},{\"attribute\": \"name\",\"count\": 61,\"type\": \"string\",\"values\": [\"BELSH\",\"BERAT\",\"BULQIZË\",\"CËRRIK\",\"DELVINË\",\"DEVOLL\",\"DIBËR\",\"DIVJAKË\",\"DROPULL\",\"DURRËS\",\"ELBASAN\",\"FIER\",\"FINIQ\",\"FUSHË ARRËS\",\"GJIROKASTËR\",\"GRAMSH\",\"HAS\",\"HIMARË\",\"KAMËZ\",\"KAVAJË\",\"KLOS\",\"KOLONJË\",\"KONISPOL\",\"KORÇË\",\"KRUJË\",\"KUKËS\",\"KURBIN\",\"KUÇOVË\",\"KËLCYRË\",\"LEZHË\",\"LIBOHOVË\",\"LIBRAZHD\",\"LUSHNJE\",\"MALIQ\",\"MALLAKASTËR\",\"MALËSI E MADHE\",\"MAT\",\"MEMALIAJ\",\"MIRDITË\",\"PATOS\",\"PEQIN\",\"POGRADEC\",\"POLIÇAN\",\"PRRENJAS\",\"PUKË\",\"PUSTEC\",\"PËRMET\",\"ROSKOVEC\",\"RROGOZHINË\",\"SARANDË\",\"SELENICË\",\"SHIJAK\",\"SHKODËR\",\"SKRAPAR\",\"TEPELENË\",\"TIRANË\",\"TROPOJË\",\"URA VAJGURORE\",\"VAU I DEJËS\",\"VLORË\",\"VORË\"]}]},{\"layer\": \"Pipe\",\"count\": 10,\"geometry\": \"LineString\",\"attributeCount\": 1,\"attributes\": [{\"attribute\": \"UtilityDeliveryTypeValue\",\"count\": 1,\"type\": \"string\",\"values\": [\"collection\"]}]},{\"layer\": \"Pole\",\"count\": 140086,\"geometry\": \"Point\",\"attributeCount\": 1,\"attributes\": [{\"attribute\": \"AsigPoleTypeValue\",\"count\": 3,\"type\": \"string\",\"values\": [\"lightningPole\",\"otherPole\",\"trafficLight\"]}]},{\"layer\": \"PortArea\",\"count\": 15,\"geometry\": \"Polygon\",\"attributeCount\": 0,\"attributes\": []},{\"layer\": \"ProductionBuilding\",\"count\": 7642,\"geometry\": \"Polygon\",\"attributeCount\": 2,\"attributes\": [{\"attribute\": \"GeographicalName\",\"count\": 151,\"type\": \"string\",\"values\": [\" \",\"\\\"Adushaj Konstruksion\\\"\",\"\\\"Afm Distribution Sh.P.K\\\"\",\"\\\"Aiba Company\\\"\",\"\\\"Alb-Zdrukth\\\"\",\"\\\"Albaco Shoes Shpk\\\"\",\"\\\"Alban Costruzion Group\\\"\",\"\\\"Albtir Sh.P.K\\\"\",\"\\\"Algida\\\"\",\"\\\"Anoria\\\"\",\"\\\"Atlas\\\"\",\"\\\"Bashllarët Shpk\\\"\",\"\\\"Berxhan Sh.P.K\\\"\",\"\\\"Brati Ulluqe\\\"\",\"\\\"Ccbs Shpk\\\"\",\"\\\"Cotex\\\"\",\"\\\"D Print Europe\\\"\",\"\\\"DHL\\\" / \\\"Evita\\\"\",\"\\\"Dea Print\\\"\",\"\\\"Derby\\\"\",\"\\\"Edil. Centro\\\"\",\"\\\"Ehw\\\"\",\"\\\"Endi Sh.p.k.\\\"\",\"\\\"Epta Company\\\"\",\"\\\"Erda\\\"\",\"\\\"Erica\\\" Hidrosanitare\",\"\\\"Euroasia\\\"\",\"\\\"Everest Ie\\\"\",\"\\\"Everest Shpk\\\"\",\"\\\"G&B\\\"\",\"\\\"Gulit\\\"\",\"\\\"Halili\\\" Beton\",\"\\\"Hesarens\\\"\",\"\\\"Hodo-Alb Shpk\\\"\",\"\\\"Home Automatica Specialist\\\"\",\"\\\"IN\\\" TV\",\"\\\"Izoterm\\\"\",\"\\\"Kbe\\\"\",\"\\\"Kolonat\\\"\",\"\\\"Kresha\\\"\",\"\\\"Lesna\\\"\",\"\\\"Metabo\\\"\",\"\\\"Miell Tirana\\\"\",\"\\\"Mon Cheri\\\"\",\"\\\"Nesim Sh.P.K\\\"\",\"\\\"News 24\\\"\",\"\\\"Niku\\\"\",\"\\\"Pascalino\\\"\",\"\\\"Pasidoni\\\"\",\"\\\"Pirraçi-U6\\\"\",\"\\\"Policam\\\"\",\"\\\"Profarma\\\"\",\"\\\"Qarri 02 Sh.P.K\\\"\",\"\\\"Rea'S Factory Sh.P.K\\\"\",\"\\\"Remal Sh.P.K\\\"\",\"\\\"Rofix\\\"\",\"\\\"Rossman & Lala\\\"\",\"\\\"Sidenor\\\" Metal Center\",\"\\\"Sina 98\\\"\",\"\\\"Soni Dural\\\"\",\"\\\"T.T.A. Alba-Lam\\\" Shpk\",\"\\\"Tenda Ozuni\\\"\",\"\\\"Textile Service Shpk\\\"\",\"\\\"Tw & Tc\\\"\",\"\\\"Univers\\\"\",\"Agro Blend\",\"Albaco Shoes\",\"Albafoam\",\"Albesol\",\"Albtelecom\",\"Arkensi Cosmetics \\\"Rayjon'S\\\"\",\"Balduci S.P.A\",\"Bashllari Sh.P.K\",\"Birra \\\"Peja\\\"\",\"Botime Pegi\",\"Concept Albania\",\"Confezione Italiane \\\"Emme & Co\\\"\",\"Construction \\\"Alb-Italia\\\"\",\"Cosmoplastica\",\"Digitalb\",\"Distileria \\\"Aquila Liquori\\\"\",\"Donianna\",\"Elisabeth\",\"Eranda Shpk Lab\",\"Fabrik Tubosh \\\"Star 2000\\\"\",\"Fabrika \\\"Dekoll\\\"\",\"Fabrika e Tullave Silikatë\",\"Fabrikave Biskotave & Kraker\",\"Fabrikë Këpucësh \\\"Albaco Shoes\\\"\",\"Fasoneri \\\"Xibritex\\\"\",\"Fortuna Sh.P.K\",\"Giulia Shoes\",\"Hako\",\"Ilgar\",\"Iliria Electric\",\"Intesa Sanpaolo Bank\",\"Ish \\\"Fabrika E Qumështit\\\"\",\"Kantina e Pijeve \\\"Gjergj Kastriot Skçnderbeu\\\"\",\"Kmy\",\"Kombinat Peshku\"]},{\"attribute\": \"sarea\",\"count\": 1000,\"type\": \"number\",\"values\": [1.1212991594794973,1.502867955266824,1.8369109991576858,1.836977320000686,1.837003280017541,1.837007559551681,1.837063739958348,1.837070400583549,1.8649609996060246,10.016870840646872,10.031158599464144,10.045209402536745,10.050175601638394,10.059507201200973,10.077180418831962,10.085130419806218,10.094238900153848,10.097157583804498,10.107751397313966,10.129543800968126,10.13780988151485,10.144023099788292,10.166770397771142,10.176825602207245,10.200544200860968,10.20742399886411,10.234171800246683,10.334696596562584,10.389036619991908,10.420984349344723,10.447578797714105,10.499776863743083,10.506707001026282,10.516397201596858,10.53481020133942,10.535784299077548,10.535784300673742,10.53578430098117,10.535784301133534,10.535784301133536,10.535784301608695,10.535784302729729,10.545856900432068,10.58682108096215,10.59987720039467,10.607402180623286,10.66149620118362,10.661496202137016,10.661496202412595,10.661496202646076,10.661496204018194,10.66149620426993,10.661496206265243,10.661496207494169,10.66149620800323,10.689642362705233,10.699319161350143,10.777357022904042,10.786592181720179,10.787941918046528,10.832235000662003,10.840339021791264,10.852119603673973,10.858632003056286,10.880113604182372,10.907575999716834,10.966640398931606,10.97254549694062,100.01191958405681,100.05469335178309,100.39581138056474,100.66750368115224,100.76608680220794,100.85985536456986,1000.8303734522838,1002.9499884525637,1003.7473380198668,1003.8043348646597,1006.5625033896387,1009.3578772047216,101.10774478573788,101.16155374749974,101.17762658917875,101.32879301354017,101.36879549542786,101.41800087493424,101.63885352668714,101.6545048115257,101.72966451370466,101.85886857809104,101.95627480378146,1011.0707412451312,1013.7000015529997,1014.660380528089,1015.1293428013703,102.06132305650482,102.16314793755335,102.18733632334402,102.33527560877605,102.36870164523852],\"min\": 1.1212991594794973,\"max\": 18581.415301083773}]},{\"layer\": \"ProductionInstallation\",\"count\": 142,\"geometry\": \"Point\",\"attributeCount\": 1,\"attributes\": [{\"attribute\": \"AsigProductionInstallationTypeValue\",\"count\": 2,\"type\": \"string\",\"values\": [\"crane\",\"industrialPylon\"]}]},{\"layer\": \"RailwayArea\",\"count\": 217,\"geometry\": \"Polygon\",\"attributeCount\": 0,\"attributes\": []},{\"layer\": \"RailwayLink\",\"count\": 701,\"geometry\": \"LineString\",\"attributeCount\": 0,\"attributes\": []},{\"layer\": \"RailwayNode\",\"count\": 24,\"geometry\": \"Point\",\"attributeCount\": 0,\"attributes\": []},{\"layer\": \"RailwayStationArea\",\"count\": 29,\"geometry\": \"Polygon\",\"attributeCount\": 0,\"attributes\": []},{\"layer\": \"RailwayStationNode\",\"count\": 3,\"geometry\": \"Point\",\"attributeCount\": 0,\"attributes\": []},{\"layer\": \"RailwayYardArea\",\"count\": 37,\"geometry\": \"Polygon\",\"attributeCount\": 0,\"attributes\": []},{\"layer\": \"RailwayYardNode\",\"count\": 33,\"geometry\": \"Point\",\"attributeCount\": 0,\"attributes\": []},{\"layer\": \"RapidsA\",\"count\": 15,\"geometry\": \"Polygon\",\"attributeCount\": 0,\"attributes\": []},{\"layer\": \"RiverBasin\",\"count\": 2350,\"geometry\": \"Polygon\",\"attributeCount\": 0,\"attributes\": []},{\"layer\": \"RoadArea\",\"count\": 2949,\"geometry\": \"Polygon\",\"attributeCount\": 0,\"attributes\": []},{\"layer\": \"RoadLink\",\"count\": 161927,\"geometry\": \"LineString\",\"attributeCount\": 1,\"attributes\": [{\"attribute\": \"GeographicalName\",\"count\": 1000,\"type\": \"string\",\"values\": [\"\",\" \",\"\\\"Autostrada Tiranë Durrës\\\"\",\"\\\"rruga \\\"Pavarësia''\",\"Arruga \\\"Akropoli''\",\"Asdreni\",\"Autostrada Elbasan - Tiranë\",\"Autostrada Tiranë - Elbasan\",\"Brruga \\\"Bajram Curri''\",\"DRINI 00690206\",\"Hyjnesha Diana\",\"Martin Camaj\",\"Pal Xhumari\",\"Rr.\\\"Xhelal Molla\\\"\",\"Rruga  Agallarëve\",\"Rruga  Ahmetaj\",\"Rruga  Akacia\",\"Rruga  Alla\",\"Rruga  Allaraj\",\"Rruga  Ballëve\",\"Rruga  Bardhosha\",\"Rruga  Begu\",\"Rruga  Bejleri\",\"Rruga  Bernoca\",\"Rruga  Blerimi\",\"Rruga  Daxhit\",\"Rruga  Demokracia\",\"Rruga  Dibranëve\",\"Rruga  Dimjanëve\",\"Rruga  Draçi\",\"Rruga  Dushkut\",\"Rruga  Fushave\",\"Rruga  Garunjës\",\"Rruga  Grori\",\"Rruga  Gërzull\",\"Rruga  Kalajve\",\"Rruga  Kokeli\",\"Rruga  Kolombo\",\"Rruga  Korabit\",\"Rruga  Kroit\",\"Rruga  Ligatave\",\"Rruga  Mucave\",\"Rruga  Myftari\",\"Rruga  Osmet\",\"Rruga  Palushi\",\"Rruga  Panorama e Liqenit\",\"Rruga  Peti\",\"Rruga  Picallëve\",\"Rruga  Pinari\",\"Rruga  Plepja\",\"Rruga  Poçeria\",\"Rruga  Rezervat e Shtetit\",\"Rruga  Shalqiz\",\"Rruga  Sheheler\",\"Rruga  Shimajve\",\"Rruga  Shkallenjëve\",\"Rruga  Shkollës\",\"Rruga  Skrreli\",\"Rruga  Topçive\",\"Rruga  Tuneleve\",\"Rruga  Ullishtës\",\"Rruga  Varrosh\",\"Rruga  Vezhnjete\",\"Rruga  Viktoria\",\"Rruga  Vilave\",\"Rruga  Vorbsi\",\"Rruga  Vrapeve\",\"Rruga  Vreshtit\",\"Rruga  Xhabrahimët\",\"Rruga  Xhani\",\"Rruga  Xhebrahimi\",\"Rruga  Xibrakëve\",\"Rruga  Zajnat\",\"Rruga  Zallit\",\"Rruga  Zambaku\",\"Rruga Kodra Diellit\",\"Rruga Kodra e Diellit\",\"Rruga Peti\",\"Rruga Rreli\",\"Rruga e Arbërit\",\"Rruga e Atjonit\",\"Rruga e Balshajve\",\"Rruga e Barrikadave\",\"Rruga e Bogdanëve\",\"Rruga e Dafinave\",\"Rruga e Dibrës\",\"Rruga e Durrësit\",\"Rruga e Elbasanit\",\"Rruga e Kavajës\",\"Rruga e Kodrës Mezez\",\"Rruga e Konjave\",\"Rruga e Kosovarëve\",\"Rruga e Kuçianëve\",\"Rruga e Limuthit\",\"Rruga e Mesme\",\"Rruga e Mimozave\",\"Rruga e Mumajezëve\",\"Rruga e Pallateve\",\"Rruga e Re\",\"Rruga e Saraçëve\"]}]},{\"layer\": \"RoadNode\",\"count\": 49510,\"geometry\": \"Point\",\"attributeCount\": 0,\"attributes\": []},{\"layer\": \"RoadServiceArea\",\"count\": 334,\"geometry\": \"Polygon\",\"attributeCount\": 0,\"attributes\": []},{\"layer\": \"RunwayArea\",\"count\": 21,\"geometry\": \"Polygon\",\"attributeCount\": 0,\"attributes\": []},{\"layer\": \"Shore\",\"count\": 1004,\"geometry\": \"Polygon\",\"attributeCount\": 1,\"attributes\": [{\"attribute\": \"ShoreTypeValue\",\"count\": 2,\"type\": \"string\",\"values\": [\"gravel\",\"sand\"]}]},{\"layer\": \"ShorelineConstruction\",\"count\": 125,\"geometry\": \"Polygon\",\"attributeCount\": 0,\"attributes\": []},{\"layer\": \"Sluice\",\"count\": 51,\"geometry\": \"Polygon\",\"attributeCount\": 0,\"attributes\": []},{\"layer\": \"SpotElevation\",\"count\": 320849,\"geometry\": \"Point\",\"attributeCount\": 3,\"attributes\": [{\"attribute\": \"HeightValue\",\"count\": 1000,\"type\": \"number\",\"values\": [-0.0120000000024447,-0.0121999999973923,-0.0170000000071013,-0.0179000000061933,-0.0198999999993248,-0.0261000000027707,-0.0282000000006519,-0.0454000000027008,-0.0500000000029104,-0.0504999999975553,-0.0531000000046333,-0.0558000000019092,-0.0561000000016065,-0.0584999999991851,-0.0599999999976717,-0.060299999997369,-0.0613000000012107,-0.0614999999961583,-0.0627999999996973,-0.0684999999939464,-0.0730000000039581,-0.0767000000050757,-0.0788000000029569,-0.0794000000023516,-0.0803000000014435,-0.0945999999967171,-0.097299999993993,-0.100000000005821,-0.104699999996228,-0.108099999997648,-0.110899999999674,-0.11250000000291,-0.113299999997253,-0.119000000006054,-0.120699999999488,-0.122399999992922,-0.122600000002421,-0.123000000006869,-0.124599999995553,-0.125400000004447,-0.130000000004657,-0.13310000000638,-0.133499999996275,-0.134000000005472,-0.134200000000419,-0.135999999998603,-0.142000000007101,-0.148499999995693,-0.150200000003679,-0.153999999994994,-0.158400000000256,-0.159899999998743,-0.162100000001374,-0.163000000000466,-0.164399999994203,-0.167000000001281,-0.170599999997648,-0.170700000002398,-0.172099999996135,-0.172500000000582,-0.173399999999674,-0.182300000000396,-0.184599999993225,-0.18739999999525,-0.189199999993434,-0.191699999995762,-0.197199999995064,-0.198300000003655,-0.202099999994971,-0.202399999994668,-0.203800000002957,-0.203999999997905,-0.205100000006496,-0.205499999996391,-0.20789999999397,-0.208100000003469,-0.208400000003166,-0.208599999998114,-0.209099999992759,-0.210800000000745,-0.211100000000442,-0.211699999999837,-0.216400000004796,-0.217000000004191,-0.21929999999702,-0.221300000004703,-0.229999999995925,-0.231199999994715,-0.232099999993807,-0.23410000000149,-0.23420000000624,-0.235000000000582,-0.236099999994622,-0.237800000002608,-0.239900000000489,-0.240300000004936,-0.242700000002515,-0.243000000002212,-0.244500000000698,-0.245200000004843],\"min\": -4.5222999999969,\"max\": 481.580400000006},{\"attribute\": \"SpotElevationClassValue\",\"count\": 2,\"type\": \"string\",\"values\": [\"building\",\"ground\"]},{\"attribute\": \"SpotElevationType\",\"count\": 4,\"type\": \"string\",\"values\": [\"depression\",\"generic\",\"pass\",\"summit\"]}]},{\"layer\": \"StandingWaterA\",\"count\": 3521,\"geometry\": \"Polygon\",\"attributeCount\": 2,\"attributes\": [{\"attribute\": \"GeographicalName\",\"count\": 17,\"type\": \"string\",\"values\": [\" \",\"Liqeni i Kasharit\",\"Liqeni i Shkozës\",\"Liqeni i Tapizës\",\"Rez. i Karreçit\",\"Rez. i Koxhasit\",\"Rez. i Mëzez\",\"Rez. i Paskuqanit\",\"Rez. i Sharra\",\"Rez. i Sharrës\",\"Ujëmb. i Gjokajt\",\"Ujëmb. i Zajës\",\"liq. i Tiranës\",\"rez.\",\"rez. i Shkallnurit\",\"ujëmb.\",\"ujëmb. i Farkës\"]},{\"attribute\": \"HydrologicalPersistenceValue\",\"count\": 2,\"type\": \"string\",\"values\": [\"intermittent\",\"perennial\"]}]},{\"layer\": \"TaxiwayArea\",\"count\": 74,\"geometry\": \"Polygon\",\"attributeCount\": 0,\"attributes\": []},{\"layer\": \"Tower\",\"count\": 1032,\"geometry\": \"Point\",\"attributeCount\": 0,\"attributes\": []},{\"layer\": \"VehicleTrafficArea\",\"count\": 36524,\"geometry\": \"Polygon\",\"attributeCount\": 1,\"attributes\": [{\"attribute\": \"AsigVehicleTrafficTypevalue\",\"count\": 8,\"type\": \"string\",\"values\": [\"bicycleLane\",\"gardenRoad\",\"highway\",\"interUrbanRoad\",\"path\",\"underconstruction\",\"urbanRoad\",\"villageLocalRoad\"]}]},{\"layer\": \"WaterManagementInstallationP\",\"count\": 3,\"geometry\": \"Point\",\"attributeCount\": 1,\"attributes\": [{\"attribute\": \"WaterSourceValue\",\"count\": 1,\"type\": \"string\",\"values\": [\"otherSources\"]}]},{\"layer\": \"WatercourseA\",\"count\": 24921,\"geometry\": \"Polygon\",\"attributeCount\": 3,\"attributes\": [{\"attribute\": \"ConditionOfFacilityValue\",\"count\": 1,\"type\": \"string\",\"values\": [\"functional\"]},{\"attribute\": \"HydrologicalPersistenceValue\",\"count\": 2,\"type\": \"string\",\"values\": [\"intermittent\",\"perennial\"]},{\"attribute\": \"VerticalPositionValue\",\"count\": 3,\"type\": \"string\",\"values\": [\"onGroundSurface\",\"suspendedOrElevated\",\"underground\"]}]},{\"layer\": \"WatercourseL\",\"count\": 35492,\"geometry\": \"LineString\",\"attributeCount\": 5,\"attributes\": [{\"attribute\": \"ConditionOfFacilityValue\",\"count\": 1,\"type\": \"string\",\"values\": [\"functional\"]},{\"attribute\": \"HydrologicalPersistenceValue\",\"count\": 2,\"type\": \"string\",\"values\": [\"intermittent\",\"perennial\"]},{\"attribute\": \"VerticalPositionValue\",\"count\": 2,\"type\": \"string\",\"values\": [\"onGroundSurface\",\"underground\"]},{\"attribute\": \"WidthRange\",\"count\": 1,\"type\": \"string\",\"values\": [\"lower\"]},{\"attribute\": \"WidthValue\",\"count\": 1000,\"type\": \"number\",\"values\": [0.00936589752371,0.0150212689006,0.0171490956736,0.0261439808998,0.029941,0.0300425153728,0.031234,0.031267,0.0313636800149,0.0318449995926,0.032004,0.03213,0.0321303452482,0.0325381093595,0.032786,0.0328790909075,0.0332472243827,0.0335205673183,0.0337617236089,0.0342093019398,0.034238889093,0.034475,0.0344750826892,0.0347679913021,0.034768,0.035232,0.036945681065,0.037273610419,0.0388979347439,0.0399778418201,0.0418344279644,0.043945,0.047413,0.0474130550328,0.0533285279423,0.05332853,0.0541706883582,0.0546988187425,0.056394,0.057603,0.0576034215733,0.0581410063534,0.0591756976298,0.0595844460545,0.059882,0.0598821379144,0.0598821826314,0.0598823037694,0.060081,0.060422,0.0605557907683,0.060889737303,0.0613543400612,0.0614864010712,0.0621762943777,0.062468,0.0624682078826,0.0624682119197,0.0625331256344,0.062663,0.062727,0.0627274862724,0.0627275073394,0.0632425900339,0.0632426717288,0.063243,0.0632946743942,0.0633367457858,0.0636899805356,0.0640077132174,0.0641447836876,0.0642405838112,0.0642607061291,0.0645755497964,0.064951,0.0649513045238,0.0650137302564,0.065014,0.0650386344223,0.065758,0.0657582326378,0.0660659205864,0.066066,0.066066031653,0.06625,0.066286,0.0662863694817,0.067703,0.0677033700629,0.0677035443405,0.0679424383575,0.0682066930235,0.068207,0.0683153358374,0.0684186344206,0.0684778203479,0.068478,0.0684780348688,0.0685962768712,0.0688325009675],\"min\": 0.00936589752371,\"max\": 4.96686794314}]},{\"layer\": \"WatercourseLink\",\"count\": 14237,\"geometry\": \"LineString\",\"attributeCount\": 1,\"attributes\": [{\"attribute\": \"GeographicalName\",\"count\": 35,\"type\": \"string\",\"values\": [\"\",\" \",\"Prr. Ligjatëve\",\"Prr. i Bojës\",\"Prr. i Farkës\",\"Prr. i Gjires\",\"Prr. i Kabatit\",\"Prr. i Kallmit\",\"Prr. i Pyllit të Djegur\",\"Prr. i Shkallës\",\"Prr. i Ujit të Mbarë\",\"Prr. i Zajve\",\"lumi i Lanës\",\"lumi i Tiranës\",\"lumi i Tërkuzës\",\"prr. I Xingeres\",\"prr. i Bojës\",\"prr. i Cerilecit\",\"prr. i Duhanit\",\"prr. i Fushës së Zonjave\",\"prr. i Gjeorezës\",\"prr. i Gjeros\",\"prr. i Hasanëve\",\"prr. i Isufajve\",\"prr. i Ligjatëve\",\"prr. i Limuthit\",\"prr. i Palpocës\",\"prr. i Peshkut\",\"prr. i Qeranës\",\"prr. i Ranzës\",\"prr. i Shargës\",\"prr. i Shkallës\",\"prr. i Surelit\",\"prr. i Xingeres\",\"prr. i Zajcës\"]}]},{\"layer\": \"WatercourseSeparatedCrossing\",\"count\": 360,\"geometry\": \"Point\",\"attributeCount\": 0,\"attributes\": []}]}}"
}
